curvesimulator/__init__.py
curvesimulator/cs_animation.py
curvesimulator/cs_bodies.py
curvesimulator/cs_body.py
curvesimulator/cs_lightcurve.py
curvesimulator/cs_parameters.py
curvesimulator/cs_physics.py
curvesimulator/cs_results.py
curvesimulator/curvesim.py
curvesimulator-0.4.3.dist-info/METADATA
curvesimulator-0.4.3.dist-info/WHEEL
curvesimulator-0.4.3.dist-info/top_level.txt
curvesimulator-0.4.3.dist-info/RECORD
