Metadata-Version: 2.2
Name: curvesimulator
Version: 0.4.3
Summary: CurveSimulator generates a video of the movements and eclipses of celestial bodies and the resulting lightcurve.
Home-page: https://github.com/lichtgestalter/curvesimulator
Author: Uli Scheuss
Classifier: Programming Language :: Python :: 3.10
Classifier: Programming Language :: Python :: 3.11
Classifier: Programming Language :: Python :: 3.12
Classifier: Programming Language :: Python :: 3.13
Classifier: License :: OSI Approved :: MIT License
Classifier: Operating System :: OS Independent
Requires-Dist: numpy
Requires-Dist: matplotlib
Requires-Dist: configparser
Dynamic: author
Dynamic: classifier
Dynamic: description
Dynamic: description-content-type
Dynamic: home-page
Dynamic: requires-dist
Dynamic: summary
